nba_apiv3/__init__.py
nba_apiv3/library/__init__.py
nba_apiv3/library/debug/__init__.py
nba_apiv3/library/debug/debug.py
nba_apiv3/library/http.py
nba_apiv3/stats/__init__.py
nba_apiv3/stats/endpoints/__init__.py
nba_apiv3/stats/endpoints/_base.py
nba_apiv3/stats/endpoints/boxscoreadvancedv3.py
nba_apiv3/stats/endpoints/boxscoredefensivev2.py
nba_apiv3/stats/endpoints/boxscorefourfactorsv3.py
nba_apiv3/stats/endpoints/boxscorehustlev2.py
nba_apiv3/stats/endpoints/boxscorematchupsv3.py
nba_apiv3/stats/endpoints/boxscoremiscv3.py
nba_apiv3/stats/endpoints/boxscoreplayertrackv3.py
nba_apiv3/stats/endpoints/boxscorescoringv3.py
nba_apiv3/stats/endpoints/boxscoretraditionalv3.py
nba_apiv3/stats/endpoints/boxscoreusagev3.py
nba_apiv3/stats/endpoints/playbyplayv3.py
nba_apiv3/stats/library/__init__.py
nba_apiv3/stats/library/data.py
nba_apiv3/stats/library/eventmsgtype.py
nba_apiv3/stats/library/http.py
nba_apiv3/stats/library/parameters.py
nba_apiv3/stats/library/parser.py
nba_apiv3/stats/library/playbyplayregex.py
nba_apiv3-0.1.1.dist-info/LICENSE
nba_apiv3-0.1.1.dist-info/METADATA
nba_apiv3-0.1.1.dist-info/WHEEL
nba_apiv3-0.1.1.dist-info/RECORD
