Metadata-Version: 2.1
Name: nba-apiv3
Version: 0.1.1
Summary: An API Client package to access the APIs version 3 for NBA.com
Home-page: https://github.com/shufinskiy/nba_apiv3
License: MIT
Keywords: api,basketball,data,nba,sports,stats
Author: Vladislav Shufinsky
Author-email: shufinsky.90210@gmail.com
Maintainer: Vladislav Shufinsky
Maintainer-email: shufinsky.90210@gmail.com
Requires-Python: >=3.8,<4.0
Classifier: Intended Audience :: Developers
Classifier: Intended Audience :: Science/Research
Classifier: License :: OSI Approved :: MIT License
Classifier: Operating System :: OS Independent
Classifier: Programming Language :: Python :: 3
Classifier: Programming Language :: Python :: 3.8
Classifier: Programming Language :: Python :: 3.9
Classifier: Programming Language :: Python :: 3.10
Classifier: Programming Language :: Python :: 3.11
Classifier: Topic :: Software Development
Requires-Dist: numpy (>=1.22.2,<2.0.0)
Requires-Dist: requests
Project-URL: Bug Tracker, https://github.com/shufinskiy/nba_apiv3/issues
Project-URL: Documentation, https://github.com/shufinskiy/nba_apiv3/blob/master/README.md
Project-URL: Repository, https://github.com/shufinskiy/nba_apiv3
